{
    "contracts_oge_active_expense":{
        "searchCriteriaMap":{
            "fiscal_year":"fiscal_year",
            "purpose":"description",
            "other_government_entities_code":"agency_code@checkbook_oge:oge_agency",
            "other_government_entities":"agency_name@checkbook_oge:agency",
            "vendor_name":"legal_name@checkbook_oge:vendor",
            "current_amount":"maximum_contract_amount",
            "spent_to_date":"spending_amount_disb",
            "award_method":"award_method_code@checkbook_oge:award_method",
            "expense_category":"expenditure_object_codes",
            "contract_id":"contract_number",
            "contract_type":"agreement_type_code",
            "start_date":"effective_begin_date",
            "end_date":"effective_end_date",
            "category":"document_code",
            "pin":"tracking_number",
            "apt_pin":"brd_awd_no",
            "is_vendor_flag":"is_vendor_flag",
            "if_for_all_years":"if_for_all_years",
            "latest_flag":"latest_flag",
            "commodity_line":"fms_commodity_line",
            "entity_contract_number":"oge_contract_number",
            "budget_name":"budget_name"
        },
        "dataset":{
            "sortColumn":[
                "-registered_date",
                "-agreement_id",
                "-fms_commodity_line",
                "-fiscal_year",
                "-type_of_year",
                "-status_flag",
                "-is_vendor_flag",
                "-if_for_all_years"
            ],
            "name":"checkbook_oge:agreement_snapshot_oge",
            "columnTypes":{
                "contract_number":"like",
                "legal_name@checkbook_oge:vendor":"like",
                "commodity_line":"like",
                "entity_contract_number":"like",
                "budget_name":"contains",
                "oge_contract_number":"like",
                "description":"contains"
            },
            "displayConfiguration":{
                "xml":{
                    "rootElement":"contract_transactions",
                    "rowParentElement":"transaction",
                    "elementsColumn":{
                        "contract_id":"contract_number",
                        "purpose":"description",
                        "version":"document_version",
                        "year":"fiscal_year",
                        "parent_contract_id":"master_contract_number",
                        "original_amount":"original_contract_amount",
                        "current_amount":"maximum_contract_amount",
                        "spent_to_date":"spending_amount_disb",
                        "prime_vendor":"vendor_name",
                        "other_government_entities":"agency_name",
                        "contract_type":"agreement_type_code",
                        "award_method":"award_method_name",
                        "expense_category":"expenditure_object_names",
                        "start_date":"effective_begin_date",
                        "end_date":"effective_end_date",
                        "pin":"tracking_number",
                        "document_code":"document_code",
                        "contract_industry":"industry_type_name",
                        "commodity_line":"fms_commodity_line",
                        "entity_contract_number":"oge_contract_number",
                        "budget_name":"budget_name"
                    },
                    "rowElements":["other_government_entities", "prime_vendor", "contract_id", "version", "year", "parent_contract_id", "purpose", "original_amount",
                        "current_amount", "spent_to_date","apt_pin", "pin", "contract_type", "award_method", "expense_category", "start_date", "end_date", "document_code",
                        "contract_industry","commodity_line","entity_contract_number","budget_name"]
                },
                "csv":{
                    "elementsColumn":{
                        "Contract ID":"contract_number",
                        "Purpose":"description",
                        "Version":"document_version",
                        "Year":"fiscal_year",
                        "Parent Contract ID":"master_contract_number",
                        "Original Amount":"original_contract_amount",
                        "Current Amount":"maximum_contract_amount",
                        "Spent to date":"spending_amount_disb",
                        "Prime Vendor":"vendor_name",
                        "Other Government Entities":"agency_name",
                        "Contract Type":"agreement_type_name",
                        "Award Method":"award_method_name",
                        "Expense Category":"expenditure_object_names",
                        "Start Date":"effective_begin_date",
                        "End Date":"effective_end_date",
                        "PIN":"tracking_number",
                        "APT":"brd_awd_no",
                        "Document Code":"document_code",
                        "Contract Industry":"industry_type_name",
                        "Commodity Line":"fms_commodity_line",
                        "Entity Contract #":"oge_contract_number",
                        "Budget Name":"budget_name"
                    }
                }
            },
            "adjustParameters":"if(function_exists('checkbook_api_adjustContractParameterFilters')){checkbook_api_adjustContractParameterFilters($data_set,$parameters,$criteria,'checkbook_oge');}"
        },
        "requestParameters":{
            "fiscal_year":{"valueType":"value","dataType":"year","maxLength":"4"},
            "other_government_entities_code":{"valueType":"value","dataType":"text","maxLength":"4"},
            "purpose":{"valueType":"value","dataType":"text","maxLength":"100"},
            "prime_vendor":{"valueType":"value","dataType":"text","maxLength":"100"},
            "current_amount":{"valueType":"range","dataType":"amount","maxLength":"18"},
            "spent_to_date":{"valueType":"range","dataType":"amount","maxLength":"18"},
            "award_method":{"valueType":"value","dataType":"text","maxLength":"3"},
            "expense_category":{"valueType":"value","dataType":"text","maxLength":"4"},
            "contract_id":{"valueType":"value","dataType":"text","maxLength":"32"},
            "contract_type":{"valueType":"value","dataType":"text","maxLength":"2"},
            "start_date":{"valueType":"range","dataType":"date","format":"YYYY-MM-DD"},
            "end_date":{"valueType":"range","dataType":"date","format":"YYYY-MM-DD"},
            "status":{"valueType":"value","dataType":"text"},
            "category":{"valueType":"value","dataType":"list","allowedValues":["expense", "revenue"]},
            "pin":{"valueType":"value","dataType":"text"},
            "apt_pin":{"valueType":"value","dataType":"text"},
            "is_vendor_flag":{"valueType":"value","dataType":"text"},
            "if_for_all_years":{"valueType":"value","dataType":"text"},
            "latest_flag":{"valueType":"value","dataType":"text"},
            "budget_name":{"valueType":"value","dataType":"text","maxLength":"75"},
            "entity_contract_number":{"valueType":"value","dataType":"text","maxLength":"15"} ,
            "commodity_line":{"valueType":"value","dataType":"text","maxLength":"3"}
        }
    },
    "contracts_oge_active_expense_all_years":{
        "searchCriteriaMap":{
            "other_government_entities_code":"agency_code@checkbook_oge:oge_agency",
            "other_government_entities":"agency_name@checkbook_oge:agency",
            "vendor_name":"legal_name@checkbook_oge:vendor",
            "purpose":"description",
            "current_amount":"maximum_contract_amount",
            "spent_to_date":"spending_amount_disb",
            "award_method":"award_method_code@checkbook_oge:award_method",
            "expense_category":"expenditure_object_codes",
            "contract_id":"contract_number",
            "contract_type":"agreement_type_code",
            "start_date":"effective_begin_date",
            "end_date":"effective_end_date",
            "category":"document_code",
            "pin":"tracking_number",
            "apt_pin":"brd_awd_no",
            "is_vendor_flag":"is_vendor_flag",
            "if_for_all_years":"if_for_all_years",
            "latest_flag":"latest_flag",
            "commodity_line":"fms_commodity_line",
            "entity_contract_number":"oge_contract_number",
            "budget_name":"budget_name"
        },
        "dataset":{
            "sortColumn":[
                "-registered_date",
                "-agreement_id",
                "-fms_commodity_line",
                "-fiscal_year",
                "-type_of_year",
                "-status_flag",
                "-is_vendor_flag",
                "-if_for_all_years"
            ],
            "name":"checkbook_oge:agreement_snapshot_oge",
            "columnTypes":{
                "expenditure_object_codes":"trueLike",
                "contract_number":"like",
                "legal_name@checkbook_oge:vendor":"like",
                "commodity_line":"like",
                "entity_contract_number":"like",
                "budget_name":"contains",
                "oge_contract_number":"like",
                "description":"contains"
            },
            "displayConfiguration":{
                "xml":{
                    "rootElement":"contract_transactions",
                    "rowParentElement":"transaction",
                    "elementsColumn":{
                        "contract_id":"contract_number",
                        "purpose":"description",
                        "version":"document_version",
                        "year":"fiscal_year",
                        "parent_contract_id":"master_contract_number",
                        "original_amount":"original_contract_amount",
                        "current_amount":"maximum_contract_amount",
                        "spent_to_date":"spending_amount_disb",
                        "prime_vendor":"vendor_name",
                        "other_government_entities":"agency_name",
                        "contract_type":"agreement_type_code",
                        "award_method":"award_method_name",
                        "expense_category":"expenditure_object_names",
                        "start_date":"effective_begin_date",
                        "end_date":"effective_end_date",
                        "pin":"tracking_number",
                        "apt_pin":"brd_awd_no",
                        "document_code":"document_code",
                        "contract_industry":"industry_type_name",
                        "commodity_line":"fms_commodity_line",
                        "entity_contract_number":"oge_contract_number",
                        "budget_name":"budget_name"
                    },
                    "rowElements":["other_government_entities", "prime_vendor", "contract_id", "version", "parent_contract_id", "purpose", "original_amount", "current_amount",
                        "spent_to_date"
                        , "apt_pin", "pin", "contract_type", "award_method", "expense_category", "start_date", "end_date", "document_code", "contract_industry"
                        ,"entity_contract_number","budget_name","commodity_line"]
                },
                "csv":{
                    "elementsColumn":{
                        "Contract ID":"contract_number",
                        "Purpose":"description",
                        "Version":"document_version",
                        "Year":"fiscal_year",
                        "Parent Contract ID":"master_contract_number",
                        "Original Amount":"original_contract_amount",
                        "Current Amount":"maximum_contract_amount",
                        "Spent to date":"spending_amount_disb",
                        "Prime Vendor":"vendor_name",
                        "Other Government Entities":"agency_name",
                        "Contract Type":"agreement_type_name",
                        "Award Method":"award_method_name",
                        "Expense Category":"expenditure_object_names",
                        "Start Date":"effective_begin_date",
                        "End Date":"effective_end_date",
                        "PIN":"tracking_number",
                        "APT":"brd_awd_no",
                        "Document Code":"document_code",
                        "Contract Industry":"industry_type_name",
                        "Commodity Line":"fms_commodity_line",
                        "Entity Contract #":"oge_contract_number",
                        "Budget Name":"budget_name"
                    }
                }
            },
            "adjustParameters":"if(function_exists('checkbook_api_adjustContractParameterFilters')){checkbook_api_adjustContractParameterFilters($data_set,$parameters,$criteria,'checkbook_oge');}"
        },
        "requestParameters":{
            "other_government_entities_code":{"valueType":"value","dataType":"text","maxLength":"4"},
            "purpose":{"valueType":"value","dataType":"text","maxLength":"100"},
            "prime_vendor":{"valueType":"value","dataType":"text","maxLength":"100"},
            "current_amount":{"valueType":"range","dataType":"amount","maxLength":"18"},
            "spent_to_date":{"valueType":"range","dataType":"amount","maxLength":"18"},
            "award_method":{"valueType":"value","dataType":"text","maxLength":"3"},
            "expense_category":{"valueType":"value","dataType":"text","maxLength":"4"},
            "contract_id":{"valueType":"value","dataType":"text","maxLength":"32"},
            "contract_type":{"valueType":"value","dataType":"text", "maxLength":"2"},
            "start_date":{"valueType":"range","dataType":"date","format":"YYYY-MM-DD"},
            "end_date":{"valueType":"range","dataType":"date","format":"YYYY-MM-DD"},
            "status":{"valueType":"value","dataType":"text"},
            "category":{"valueType":"value","dataType":"list","allowedValues":["expense", "revenue"]},
            "pin":{"valueType":"value","dataType":"text"},
            "apt_pin":{"valueType":"value","dataType":"text"},
            "budget_name":{"valueType":"value","dataType":"text","maxLength":"75"},
            "entity_contract_number":{"valueType":"value","dataType":"text","maxLength":"15"} ,
            "commodity_line":{"valueType":"value","dataType":"text","maxLength":"3"},
            "is_vendor_flag":{"valueType":"value","dataType":"text"},
            "if_for_all_years":{"valueType":"value","dataType":"text"},
            "latest_flag":{"valueType":"value","dataType":"text"}
        }
    },
    "requiredCriteria":[
        {
            "name":"status",
            "criteriaLevel":"value",
            "allowedValues":["active", "registered"]
        },
        {
            "name":"category",
            "criteriaLevel":"value",
            "allowedValues":["expense" ]
        }
    ],
    "validators":[
        {
            "name":"optionalSingleFilter",
            "configKey":["contracts_oge_active_expense", "contracts_oge_active_revenue"],
            "config":{
                "criteriaLevel":"value",
                "validatorType":"filterName",
                "validatorTypeConfig":{
                    "required":false,
                    "filterNames":["fiscal_year"]
                }
            }
        }
    ]
}